.gitignore
.travis.yml
CHANGES.md
LICENSE
MANIFEST.in
README.md
requirements.txt
setup.py
examples/bug - check other datatypes.ipynb
examples/grouplabelencode.ipynb
grouplabelencode/__init__.py
grouplabelencode/grouplabelencode_func.py
grouplabelencode.egg-info/PKG-INFO
grouplabelencode.egg-info/SOURCES.txt
grouplabelencode.egg-info/dependency_links.txt
grouplabelencode.egg-info/not-zip-safe
grouplabelencode.egg-info/requires.txt
grouplabelencode.egg-info/top_level.txt
profile/funcalls (prun).ipynb
profile/generatedata.ipynb
profile/linebyline (lprun).ipynb
profile/memory (mprun).ipynb
profile/speed (timeit).ipynb
test/__init__.py
test/test_grouplabelencode.py