Metadata-Version: 2.1
Name: grouplabelencode
Version: 0.1.2
Summary: Encode grouped labels
Home-page: http://github.com/kmedian/grouplabelencode
Author: Ulf Hamster
Author-email: 554c46@gmail.com
License: MIT
Platform: UNKNOWN
Requires-Python: >=3.6
